odoo/addons/web_tree_dynamic_colored_field/README.rst
odoo/addons/web_tree_dynamic_colored_field/__init__.py
odoo/addons/web_tree_dynamic_colored_field/__manifest__.py
odoo/addons/web_tree_dynamic_colored_field/demo/res_users.xml
odoo/addons/web_tree_dynamic_colored_field/i18n/es.po
odoo/addons/web_tree_dynamic_colored_field/i18n/fi.po
odoo/addons/web_tree_dynamic_colored_field/i18n/fr.po
odoo/addons/web_tree_dynamic_colored_field/i18n/it.po
odoo/addons/web_tree_dynamic_colored_field/i18n/nl_NL.po
odoo/addons/web_tree_dynamic_colored_field/i18n/sl.po
odoo/addons/web_tree_dynamic_colored_field/i18n/web_tree_dynamic_colored_field.pot
odoo/addons/web_tree_dynamic_colored_field/i18n/zh_CN.po
odoo/addons/web_tree_dynamic_colored_field/readme/CONTRIBUTORS.md
odoo/addons/web_tree_dynamic_colored_field/readme/CREDITS.md
odoo/addons/web_tree_dynamic_colored_field/readme/DESCRIPTION.md
odoo/addons/web_tree_dynamic_colored_field/readme/ROADMAP.md
odoo/addons/web_tree_dynamic_colored_field/readme/USAGE.md
odoo/addons/web_tree_dynamic_colored_field/static/description/icon.png
odoo/addons/web_tree_dynamic_colored_field/static/description/index.html
odoo/addons/web_tree_dynamic_colored_field/static/src/js/list_renderer.esm.js
odoo/addons/web_tree_dynamic_colored_field/static/src/xml/list.xml
odoo_addon_web_tree_dynamic_colored_field-18.0.1.0.1.dist-info/METADATA
odoo_addon_web_tree_dynamic_colored_field-18.0.1.0.1.dist-info/WHEEL
odoo_addon_web_tree_dynamic_colored_field-18.0.1.0.1.dist-info/top_level.txt
odoo_addon_web_tree_dynamic_colored_field-18.0.1.0.1.dist-info/RECORD
